[
  {
    "num": "周四001",
    "match_time": "2017-06-22 23:00",
    "matchId": "933173",
    "league": "联合会杯",
    "home": "喀麦隆",
    "away": "澳大利亚",
    "result": {
      "half": "1-0",
      "full": "1-1",
      "win_draw_lose_result": "1",
      "win_draw_lose_odds": "3.200",
      "handicap": "-1",
      "handicap_result": "0",
      "handicap_odds": "1.340",
      "score_result": "1:1",
      "score_odds": "6.500",
      "goal_result": "2",
      "goal_odds": "3.250",
      "half_full_result": "3-1",
      "half_full_odds": "13.000"
    }
  },
  {
    "num": "周四002",
    "match_time": "2017-06-22 02:00",
    "matchId": "926373",
    "league": "联合会杯",
    "home": "德国",
    "away": "智利",
    "result": {
      "half": "1-1",
      "full": "1-1",
      "win_draw_lose_result": "1",
      "win_draw_lose_odds": "3.300",
      "handicap": "-1",
      "handicap_result": "0",
      "handicap_odds": "1.460",
      "score_result": "1:1",
      "score_odds": "6.300",
      "goal_result": "2",
      "goal_odds": "3.500",
      "half_full_result": "1-1",
      "half_full_odds": "5.100"
    }
  },
  {
    "num": "周四003",
    "match_time": "2017-06-22 02:00",
    "matchId": "906314",
    "league": "阿甲",
    "home": "贝尔格拉诺",
    "away": "纽维尔老男孩",
    "result": {
      "half": "1-0",
      "full": "2-1",
      "win_draw_lose_result": "3",
      "win_draw_lose_odds": "4.100",
      "handicap": "+1",
      "handicap_result": "3",
      "handicap_odds": "1.770",
      "score_result": "2:1",
      "score_odds": "10.500",
      "goal_result": "3",
      "goal_odds": "3.800",
      "half_full_result": "3-3",
      "half_full_odds": "5.400"
    }
  },
  {
    "num": "周四004",
    "match_time": "2017-06-22 02:45",
    "matchId": "951770",
    "league": "U21欧洲杯",
    "home": "波兰U21",
    "away": "英格兰U21",
    "result": {
      "half": "0-1",
      "full": "0-3",
      "win_draw_lose_result": "0",
      "win_draw_lose_odds": "1.430",
      "handicap": "+1",
      "handicap_result": "0",
      "handicap_odds": "2.530",
      "score_result": "0:3",
      "score_odds": "10.000",
      "goal_result": "3",
      "goal_odds": "3.300",
      "half_full_result": "0-0",
      "half_full_odds": "1.900"
    }
  },
  {
    "num": "周四005",
    "match_time": "2017-06-22 02:45",
    "matchId": "951769",
    "league": "U21欧洲杯",
    "home": "斯洛伐克U21",
    "away": "瑞典U21",
    "result": {
      "half": "2-0",
      "full": "3-0",
      "win_draw_lose_result": "3",
      "win_draw_lose_odds": "2.800",
      "handicap": "+1",
      "handicap_result": "3",
      "handicap_odds": "1.560",
      "score_result": "3:0",
      "score_odds": "25.000",
      "goal_result": "3",
      "goal_odds": "3.300",
      "half_full_result": "3-3",
      "half_full_odds": "4.300"
    }
  },
  {
    "num": "周四006",
    "match_time": "2017-06-22 04:10",
    "matchId": "906326",
    "league": "阿甲",
    "home": "拉努斯",
    "away": "飓风",
    "result": {
      "half": "0-0",
      "full": "2-0",
      "win_draw_lose_result": "3",
      "win_draw_lose_odds": "1.490",
      "handicap": "-1",
      "handicap_result": "3",
      "handicap_odds": "2.840",
      "score_result": "2:0",
      "score_odds": "5.900",
      "goal_result": "2",
      "goal_odds": "2.800",
      "half_full_result": "1-3",
      "half_full_odds": "4.050"
    }
  },
  {
    "num": "周四007",
    "match_time": "2017-06-22 04:10",
    "matchId": "906325",
    "league": "阿甲",
    "home": "萨米恩托",
    "away": "天主教青年会",
    "result": {
      "half": "1-1",
      "full": "1-3",
      "win_draw_lose_result": "0",
      "win_draw_lose_odds": "2.330",
      "handicap": "+1",
      "handicap_result": "0",
      "handicap_odds": "5.260",
      "score_result": "1:3",
      "score_odds": "18.000",
      "goal_result": "4",
      "goal_odds": "5.800",
      "half_full_result": "1-0",
      "half_full_odds": "5.000"
    }
  },
  {
    "num": "周四008",
    "match_time": "2017-06-22 06:20",
    "matchId": "906320",
    "league": "阿甲",
    "home": "老虎竞技",
    "away": "拉斐拉竞技",
    "result": {
      "half": "0-0",
      "full": "1-0",
      "win_draw_lose_result": "3",
      "win_draw_lose_odds": "1.620",
      "handicap": "-1",
      "handicap_result": "1",
      "handicap_odds": "3.300",
      "score_result": "1:0",
      "score_odds": "5.500",
      "goal_result": "1",
      "goal_odds": "4.100",
      "half_full_result": "1-3",
      "half_full_odds": "4.200"
    }
  },
  {
    "num": "周四009",
    "match_time": "2017-06-22 06:20",
    "matchId": "906317",
    "league": "阿甲",
    "home": "戈多伊克鲁斯",
    "away": "拉普拉塔大学生",
    "result": {
      "half": "0-1",
      "full": "0-2",
      "win_draw_lose_result": "0",
      "win_draw_lose_odds": "2.300",
      "handicap": "+1",
      "handicap_result": "0",
      "handicap_odds": "5.150",
      "score_result": "0:2",
      "score_odds": "9.000",
      "goal_result": "2",
      "goal_odds": "3.050",
      "half_full_result": "0-0",
      "half_full_odds": "3.700"
    }
  },
  {
    "num": "周四010",
    "match_time": "2017-06-22 06:30",
    "matchId": "944792",
    "league": "巴西甲",
    "home": "庞特普雷塔",
    "away": "克鲁塞罗",
    "result": {
      "half": "1-0",
      "full": "1-0",
      "win_draw_lose_result": "3",
      "win_draw_lose_odds": "2.140",
      "handicap": "-1",
      "handicap_result": "1",
      "handicap_odds": "3.700",
      "score_result": "1:0",
      "score_odds": "6.000",
      "goal_result": "1",
      "goal_odds": "3.550",
      "half_full_result": "3-3",
      "half_full_odds": "3.700"
    }
  },
  {
    "num": "周四011",
    "match_time": "2017-06-22 06:30",
    "matchId": "944877",
    "league": "巴西甲",
    "home": "科林蒂安",
    "away": "巴伊亚",
    "result": {
      "half": "1-0",
      "full": "3-0",
      "win_draw_lose_result": "3",
      "win_draw_lose_odds": "1.300",
      "handicap": "-1",
      "handicap_result": "3",
      "handicap_odds": "2.210",
      "score_result": "3:0",
      "score_odds": "8.700",
      "goal_result": "3",
      "goal_odds": "3.700",
      "half_full_result": "3-3",
      "half_full_odds": "1.850"
    }
  },
  {
    "num": "周四012",
    "match_time": "2017-06-22 08:00",
    "matchId": "944787",
    "league": "巴西甲",
    "home": "弗拉门戈",
    "away": "沙佩科恩斯",
    "result": {
      "half": "2-0",
      "full": "5-1",
      "win_draw_lose_result": "3",
      "win_draw_lose_odds": "1.330",
      "handicap": "-1",
      "handicap_result": "3",
      "handicap_odds": "2.180",
      "score_result": "5:1",
      "score_odds": "50.000",
      "goal_result": "6",
      "goal_odds": "19.000",
      "half_full_result": "3-3",
      "half_full_odds": "1.850"
    }
  },
  {
    "num": "周四013",
    "match_time": "2017-06-22 08:00",
    "matchId": "944810",
    "league": "巴西甲",
    "home": "格雷米奥",
    "away": "科里蒂巴",
    "result": {
      "half": "1-0",
      "full": "2-0",
      "win_draw_lose_result": "3",
      "win_draw_lose_odds": "1.430",
      "handicap": "-1",
      "handicap_result": "3",
      "handicap_odds": "2.590",
      "score_result": "2:0",
      "score_odds": "5.650",
      "goal_result": "2",
      "goal_odds": "3.100",
      "half_full_result": "3-3",
      "half_full_odds": "2.020"
    }
  },
  {
    "num": "周四014",
    "match_time": "2017-06-22 08:30",
    "matchId": "906333",
    "league": "阿甲",
    "home": "圣菲联合",
    "away": "阿根廷独立",
    "result": {
      "half": "0-1",
      "full": "0-3",
      "win_draw_lose_result": "0",
      "win_draw_lose_odds": "1.590",
      "handicap": "+1",
      "handicap_result": "0",
      "handicap_odds": "3.110",
      "score_result": "0:3",
      "score_odds": "12.000",
      "goal_result": "3",
      "goal_odds": "3.750",
      "half_full_result": "0-0",
      "half_full_odds": "2.400"
    }
  },
  {
    "num": "周四015",
    "match_time": "2017-06-22 08:30",
    "matchId": "906321",
    "league": "阿甲",
    "home": "图库曼竞技",
    "away": "萨斯菲尔德",
    "result": {
      "half": "1-1",
      "full": "1-1",
      "win_draw_lose_result": "1",
      "win_draw_lose_odds": "3.000",
      "handicap": "-1",
      "handicap_result": "0",
      "handicap_odds": "1.450",
      "score_result": "1:1",
      "score_odds": "6.000",
      "goal_result": "2",
      "goal_odds": "3.150",
      "half_full_result": "1-1",
      "half_full_odds": "4.300"
    }
  }
]